ruleapp/LocationDTO.py
ruleapp/__init__.py
ruleapp/DBconnection/RedisConnectionImpl.py
ruleapp/DBconnection/__init__.py
ruleapp/Devices/DeviceEvaluationDTO.py
ruleapp/Devices/DeviceId.py
ruleapp/Devices/__init__.py
ruleapp/Devices/Alert/AlertConsequentDTO.py
ruleapp/Devices/Alert/AlertConsequentFunctions.py
ruleapp/Devices/Alert/AlertDTO.py
ruleapp/Devices/Alert/AlertFunctions.py
ruleapp/Devices/Alert/__init__.py
ruleapp/Devices/Button/ButtonAntecedentDTO.py
ruleapp/Devices/Button/ButtonAntecedentFunctions.py
ruleapp/Devices/Button/ButtonDTO.py
ruleapp/Devices/Button/ButtonFunctions.py
ruleapp/Devices/Button/__init__.py
ruleapp/Devices/Photocell/PhotocellAntecedentDTO.py
ruleapp/Devices/Photocell/PhotocellAntecedentFunctions.py
ruleapp/Devices/Photocell/PhotocellDTO.py
ruleapp/Devices/Photocell/PhotocellFunctions.py
ruleapp/Devices/Photocell/__init__.py
ruleapp/Devices/Servo/ServoConsequentDTO.py
ruleapp/Devices/Servo/ServoConsequentFunctions.py
ruleapp/Devices/Servo/ServoDTO.py
ruleapp/Devices/Servo/ServoFunctions.py
ruleapp/Devices/Servo/__init__.py
ruleapp/Devices/Switch/SwitchAntecedentDTO.py
ruleapp/Devices/Switch/SwitchAntecedentFunctions.py
ruleapp/Devices/Switch/SwitchConsequentDTO.py
ruleapp/Devices/Switch/SwitchConsequentFunctions.py
ruleapp/Devices/Switch/SwitchDTO.py
ruleapp/Devices/Switch/SwitchFuntions.py
ruleapp/Devices/Switch/__init__.py
ruleapp/Devices/Timer/TimerAntecedentDTO.py
ruleapp/Devices/Timer/TimerAntecedentFunctions.py
ruleapp/Devices/Timer/TimerDTO.py
ruleapp/Devices/Timer/TimerFunctions.py
ruleapp/Devices/Timer/__init__.py
ruleapp/Devices/WaterLevel/WaterLevelAntecedentDTO.py
ruleapp/Devices/WaterLevel/WaterLevelAntecedentFunctions.py
ruleapp/Devices/WaterLevel/WaterLevelDTO.py
ruleapp/Devices/WaterLevel/WaterLevelFunctions.py
ruleapp/Devices/WaterLevel/__init__.py
ruleapp/Devices/Weather/LocationDTO.py
ruleapp/Devices/Weather/WeatherAntecedentDTO.py
ruleapp/Devices/Weather/WeatherAntecedentFunctions.py
ruleapp-0.11.4.dist-info/METADATA
ruleapp-0.11.4.dist-info/WHEEL
ruleapp-0.11.4.dist-info/top_level.txt
ruleapp-0.11.4.dist-info/RECORD
