Metadata-Version: 2.1
Name: ruleapp
Version: 0.11.4
Summary: ruleapp dto library
Home-page: UNKNOWN
Author: Giovanni Di Martino
Author-email: giovanni.dimartino1994@gmail.com
License: UNKNOWN
Platform: UNKNOWN
Classifier: Programming Language :: Python :: 3
Classifier: Operating System :: OS Independent
